cp210x/__init__.py
cp210x/cp210x.py
cp210x/eeprom.py
cp210x/valuefile.py
kw_cp210x_program-0.4.1.data/scripts/cp210x-program.py
kw_cp210x_program-0.4.1.dist-info/LICENSE
kw_cp210x_program-0.4.1.dist-info/METADATA
kw_cp210x_program-0.4.1.dist-info/WHEEL
kw_cp210x_program-0.4.1.dist-info/top_level.txt
kw_cp210x_program-0.4.1.dist-info/RECORD
