Metadata-Version: 2.1
Name: kw-cp210x-program
Version: 0.4.1
Summary: Provides access to the EEPROM in an Silabs CP210x
Home-page: https://github.com/VCTLabs/cp210x-program
Author: Johannes Hölzl
Author-email: johannes.hoelzl@gmx.de
License: attr: cp210x.__license__
Platform: POSIX
Classifier: License :: OSI Approved :: GNU Library or Lesser General Public License (LGPL)
Classifier: Intended Audience :: Manufacturing
Classifier: Development Status :: 4 - Beta
Classifier: Topic :: System :: Hardware :: Hardware Drivers
Classifier: Programming Language :: Python
Classifier: Operating System :: POSIX :: Linux
Classifier: Operating System :: POSIX :: BSD :: FreeBSD
Classifier: Operating System :: MacOS :: MacOS X
License-File: LICENSE
